DESCRIPTION.rst
LICENSE
MANIFEST.in
setup.py
py_rt.egg-info/PKG-INFO
py_rt.egg-info/SOURCES.txt
py_rt.egg-info/dependency_links.txt
py_rt.egg-info/requires.txt
py_rt.egg-info/top_level.txt
pyrt/__init__.py
pyrt/pyrt.py