Metadata-Version: 1.1
Name: py-rt
Version: 0.2.2
Summary: Low-level API for Request tracker 4
Home-page: https://github.com/dvoraka/py-rt
Author: dvoraka
Author-email: alen.dvorak@gmail.com
License: GPLv3
Keywords: rt4 helpdesk request tracker
Platform: UNKNOWN
Classifier: Development Status :: 5 - Production/Stable
Classifier: Intended Audience :: Developers
Classifier: Topic :: Software Development :: Libraries
Classifier: License :: OSI Approved :: GNU General Public License v3 (GPLv3)
Classifier: Programming Language :: Python :: 2
Classifier: Programming Language :: Python :: 2.7
